bhargabchi/__init__.py
bhargabchi-0.0.1.dist-info/LICENSE
bhargabchi-0.0.1.dist-info/METADATA
bhargabchi-0.0.1.dist-info/WHEEL
bhargabchi-0.0.1.dist-info/top_level.txt
bhargabchi-0.0.1.dist-info/RECORD
