Metadata-Version: 2.1
Name: bhargabchi
Version: 0.0.1
Summary: Chi sqaure applied to use directly
Author: Bhargab
Author-email: bhargab.ganguli@gmail.com
License: MIT
Keywords: chi2,dof,exp,exp_table,p,pvalue,expected,degreeoffreedom,chivalue
Classifier: Development Status :: 3 - Alpha
Classifier: Intended Audience :: Developers
Classifier: Topic :: Software Development :: Build Tools
Classifier: License :: OSI Approved :: MIT License
Classifier: Programming Language :: Python :: 3
License-File: LICENSE
Requires-Dist: scipy
Requires-Dist: pandas
Requires-Dist: numpy
